{
  "project_info": {
    "project_number": "919279267186",
    "project_id": "helping-hand-33585",
    "storage_bucket": "helping-hand-33585.appspot.com"
  },
  "client": [
    {
      "client_info": {
        "mobilesdk_app_id": "1:919279267186:android:a9a28ad7ffff8dd07c41eb",
        "android_client_info": {
          "package_name": "com.example.helpinghand"
        }
      },
      "oauth_client": [
        {
          "client_id": "919279267186-0t828tvjmthj9r23p89rucuond3fr39l.apps.googleusercontent.com",
          "client_type": 3
        }
      ],
      "api_key": [
        {
          "current_key": "AIzaSyBPwa2qXzJHUvb8uxjyhwe-Ne5H7T2aqjU"
        }
      ],
      "services": {
        "appinvite_service": {
          "other_platform_oauth_client": [
            {
              "client_id": "919279267186-0t828tvjmthj9r23p89rucuond3fr39l.apps.googleusercontent.com",
              "client_type": 3
            }
          ]
        }
      }
    }
  ],
  "configuration_version": "1"
}